.hgignore
LICENSE
README.rst
setup.py
django_powerdns.egg-info/PKG-INFO
django_powerdns.egg-info/SOURCES.txt
django_powerdns.egg-info/dependency_links.txt
django_powerdns.egg-info/requires.txt
django_powerdns.egg-info/top_level.txt
example/README.rst
example/__init__.py
example/manage.py
example/settings.py
example/urls.py
powerdns/__init__.py
powerdns/admin.py
powerdns/models.py