Metadata-Version: 1.0
Name: django-powerdns
Version: 0.2
Summary: PowerDNS administration module for Django
Home-page: http://bitbucket.org/peternixon/django-powerdns/
Author: Peter Nixon
Author-email: listuser@peternixon.net
License: BSD
Download-URL: http://bitbucket.org/peternixon/django-powerdns/downloads/
Platform: any
Classifier: Development Status :: 4 - Beta
Classifier: Framework :: Django
Classifier: Intended Audience :: Developers
Classifier: Intended Audience :: System Administrators
Classifier: License :: OSI Approved :: BSD License
Classifier: Operating System :: OS Independent
Classifier: Programming Language :: Python
Classifier: Topic :: Internet :: WWW/HTTP
Classifier: Topic :: Internet :: Name Service (DNS)
Classifier: Topic :: Internet :: WWW/HTTP :: WSGI :: Application
Classifier: Topic :: Software Development :: Libraries :: Python Modules
